pyspacewar/__init__.py
pyspacewar/ai.py
pyspacewar/game.py
pyspacewar/main.py
pyspacewar/ui.py
pyspacewar/version.py
pyspacewar/world.py
pyspacewar/fonts/LICENSE.txt
pyspacewar/fonts/NotoSans-Bold.ttf
pyspacewar/fonts/NotoSans-BoldItalic.ttf
pyspacewar/fonts/NotoSans-Italic.ttf
pyspacewar/fonts/NotoSans-Regular.ttf
pyspacewar/icons/README.txt
pyspacewar/icons/pyspacewar-gallery.png
pyspacewar/icons/pyspacewar16.png
pyspacewar/icons/pyspacewar16.svg
pyspacewar/icons/pyspacewar22.png
pyspacewar/icons/pyspacewar22.svg
pyspacewar/icons/pyspacewar32.png
pyspacewar/icons/pyspacewar32.svg
pyspacewar/icons/pyspacewar48.png
pyspacewar/icons/pyspacewar48.svg
pyspacewar/images/README.txt
pyspacewar/images/background.jpg
pyspacewar/images/planet_D3.png
pyspacewar/images/planet_E0.png
pyspacewar/images/planet_G0.png
pyspacewar/images/planet_G2.png
pyspacewar/images/planet_I0.png
pyspacewar/images/title.png
pyspacewar/music/README.txt
pyspacewar/music/music.ini
pyspacewar/sounds/Grenade2.au
pyspacewar/sounds/Grenade2.wav
pyspacewar/sounds/Gun_Silencer.wav
pyspacewar/sounds/Pink_Noise1.au
pyspacewar/sounds/Pink_Noise1.wav
pyspacewar/sounds/README.txt
pyspacewar/sounds/bomb.wav
pyspacewar/sounds/briefcs1.wav
pyspacewar/sounds/coin2.wav
pyspacewar/sounds/electricshock.wav
pyspacewar/sounds/sounds.ini
pyspacewar-1.2.0.data/scripts/pyspacewar
pyspacewar-1.2.0.dist-info/LICENSE
pyspacewar-1.2.0.dist-info/METADATA
pyspacewar-1.2.0.dist-info/WHEEL
pyspacewar-1.2.0.dist-info/top_level.txt
pyspacewar-1.2.0.dist-info/RECORD
