Metadata-Version: 2.1
Name: pyspacewar
Version: 1.2.0
Summary: A game loosely inspired by the original Spacewar
Home-page: https://mg.pov.lt/pyspacewar/
Author: Marius Gedminas
Author-email: marius@gedmin.as
License: GPL
Platform: any
Classifier: Development Status :: 4 - Beta
Classifier: Environment :: MacOS X
Classifier: Environment :: Win32 (MS Windows)
Classifier: Environment :: X11 Applications
Classifier: Intended Audience :: End Users/Desktop
Classifier: License :: OSI Approved :: GNU General Public License (GPL)
Classifier: Natural Language :: English
Classifier: Operating System :: OS Independent
Classifier: Programming Language :: Python :: 3.7
Classifier: Programming Language :: Python :: 3.8
Classifier: Programming Language :: Python :: 3.9
Classifier: Programming Language :: Python :: 3.10
Classifier: Programming Language :: Python :: 3.11
Classifier: Programming Language :: Python :: 3.12
Classifier: Programming Language :: Python :: 3.13
Classifier: Programming Language :: Python :: Implementation :: CPython
Classifier: Programming Language :: Python :: Implementation :: PyPy
Classifier: Topic :: Games/Entertainment :: Arcade
Requires-Python: >=3.7
License-File: LICENSE
Requires-Dist: pygame
Provides-Extra: numpy
Requires-Dist: numpy; extra == "numpy"
Provides-Extra: test
Requires-Dist: mock; extra == "test"
Requires-Dist: pytest; extra == "test"
